Metadata-Version: 2.1
Name: skypilot-nightly
Version: 1.0.0.dev2024053101
Summary: SkyPilot: An intercloud broker for the clouds
Author: SkyPilot Team
License: Apache 2.0
Project-URL: Homepage, https://github.com/skypilot-org/skypilot
Project-URL: Issues, https://github.com/skypilot-org/skypilot/issues
Project-URL: Discussion, https://github.com/skypilot-org/skypilot/discussions
Project-URL: Documentation, https://skypilot.readthedocs.io/en/latest/
Classifier: Programming Language :: Python :: 3.7
Classifier: Programming Language :: Python :: 3.8
Classifier: Programming Language :: Python :: 3.9
Classifier: Programming Language :: Python :: 3.10
Classifier: Programming Language :: Python :: 3.11
Classifier: License :: OSI Approved :: Apache Software License
Classifier: Operating System :: OS Independent
Classifier: Topic :: Software Development :: Libraries :: Python Modules
Classifier: Topic :: System :: Distributed Computing
License-File: LICENSE
Requires-Dist: wheel
Requires-Dist: cachetools
Requires-Dist: click >=7.0
Requires-Dist: colorama
Requires-Dist: cryptography
Requires-Dist: jinja2 >=3.0
Requires-Dist: jsonschema
Requires-Dist: networkx
Requires-Dist: pandas >=1.3.0
Requires-Dist: pendulum
Requires-Dist: PrettyTable >=2.0.0
Requires-Dist: python-dotenv
Requires-Dist: rich
Requires-Dist: tabulate
Requires-Dist: typing-extensions
Requires-Dist: filelock >=3.6.0
Requires-Dist: packaging
Requires-Dist: psutil
Requires-Dist: pulp
Requires-Dist: pyyaml !=5.4.*,>3.13
Requires-Dist: requests
Provides-Extra: all
Requires-Dist: urllib3 <2 ; extra == 'all'
Requires-Dist: awscli >=1.27.10 ; extra == 'all'
Requires-Dist: botocore >=1.29.10 ; extra == 'all'
Requires-Dist: boto3 >=1.26.1 ; extra == 'all'
Requires-Dist: colorama <0.4.5 ; extra == 'all'
Requires-Dist: azure-cli >=2.31.0 ; extra == 'all'
Requires-Dist: azure-core ; extra == 'all'
Requires-Dist: azure-identity >=1.13.0 ; extra == 'all'
Requires-Dist: azure-mgmt-network ; extra == 'all'
Requires-Dist: ray[default] !=2.6.0,>=2.2.0 ; extra == 'all'
Requires-Dist: google-api-python-client >=2.69.0 ; extra == 'all'
Requires-Dist: google-cloud-storage ; extra == 'all'
Requires-Dist: ibm-cloud-sdk-core ; extra == 'all'
Requires-Dist: ibm-vpc ; extra == 'all'
Requires-Dist: ibm-platform-services ; extra == 'all'
Requires-Dist: ibm-cos-sdk ; extra == 'all'
Requires-Dist: docker ; extra == 'all'
Requires-Dist: oci ; extra == 'all'
Requires-Dist: kubernetes >=20.0.0 ; extra == 'all'
Requires-Dist: protobuf !=3.19.5,>=3.15.3 ; extra == 'all'
Requires-Dist: pydantic !=2.0.*,!=2.1.*,!=2.2.*,!=2.3.*,!=2.4.*,<3 ; extra == 'all'
Requires-Dist: runpod >=1.5.1 ; extra == 'all'
Requires-Dist: cudo-compute >=0.1.10 ; extra == 'all'
Requires-Dist: pyvmomi ==8.0.1.0.2 ; extra == 'all'
Requires-Dist: grpcio !=1.48.0,<=1.51.3,>=1.32.0 ; (python_version < "3.10" and sys_platform != "darwin") and extra == 'all'
Requires-Dist: grpcio !=1.48.0,<=1.49.1,>=1.32.0 ; (python_version < "3.10" and sys_platform == "darwin") and extra == 'all'
Requires-Dist: grpcio !=1.48.0,<=1.51.3,>=1.42.0 ; (python_version >= "3.10" and sys_platform != "darwin") and extra == 'all'
Requires-Dist: grpcio !=1.48.0,<=1.49.1,>=1.42.0 ; (python_version >= "3.10" and sys_platform == "darwin") and extra == 'all'
Provides-Extra: aws
Requires-Dist: urllib3 <2 ; extra == 'aws'
Requires-Dist: awscli >=1.27.10 ; extra == 'aws'
Requires-Dist: botocore >=1.29.10 ; extra == 'aws'
Requires-Dist: boto3 >=1.26.1 ; extra == 'aws'
Requires-Dist: colorama <0.4.5 ; extra == 'aws'
Provides-Extra: azure
Requires-Dist: azure-cli >=2.31.0 ; extra == 'azure'
Requires-Dist: azure-core ; extra == 'azure'
Requires-Dist: azure-identity >=1.13.0 ; extra == 'azure'
Requires-Dist: azure-mgmt-network ; extra == 'azure'
Requires-Dist: ray[default] !=2.6.0,>=2.2.0 ; extra == 'azure'
Provides-Extra: cloudflare
Requires-Dist: urllib3 <2 ; extra == 'cloudflare'
Requires-Dist: awscli >=1.27.10 ; extra == 'cloudflare'
Requires-Dist: botocore >=1.29.10 ; extra == 'cloudflare'
Requires-Dist: boto3 >=1.26.1 ; extra == 'cloudflare'
Requires-Dist: colorama <0.4.5 ; extra == 'cloudflare'
Provides-Extra: cudo
Requires-Dist: cudo-compute >=0.1.10 ; extra == 'cudo'
Provides-Extra: docker
Requires-Dist: docker ; extra == 'docker'
Requires-Dist: ray[default] !=2.6.0,>=2.2.0 ; extra == 'docker'
Provides-Extra: fluidstack
Provides-Extra: gcp
Requires-Dist: google-api-python-client >=2.69.0 ; extra == 'gcp'
Requires-Dist: google-cloud-storage ; extra == 'gcp'
Provides-Extra: ibm
Requires-Dist: ibm-cloud-sdk-core ; extra == 'ibm'
Requires-Dist: ibm-vpc ; extra == 'ibm'
Requires-Dist: ibm-platform-services ; extra == 'ibm'
Requires-Dist: ibm-cos-sdk ; extra == 'ibm'
Requires-Dist: ray[default] !=2.6.0,>=2.2.0 ; extra == 'ibm'
Provides-Extra: kubernetes
Requires-Dist: kubernetes >=20.0.0 ; extra == 'kubernetes'
Provides-Extra: lambda
Requires-Dist: ray[default] !=2.6.0,>=2.2.0 ; extra == 'lambda'
Provides-Extra: oci
Requires-Dist: oci ; extra == 'oci'
Requires-Dist: ray[default] !=2.6.0,>=2.2.0 ; extra == 'oci'
Provides-Extra: paperspace
Provides-Extra: remote
Requires-Dist: protobuf !=3.19.5,>=3.15.3 ; extra == 'remote'
Requires-Dist: pydantic !=2.0.*,!=2.1.*,!=2.2.*,!=2.3.*,!=2.4.*,<3 ; extra == 'remote'
Requires-Dist: grpcio !=1.48.0,<=1.51.3,>=1.32.0 ; (python_version < "3.10" and sys_platform != "darwin") and extra == 'remote'
Requires-Dist: grpcio !=1.48.0,<=1.49.1,>=1.32.0 ; (python_version < "3.10" and sys_platform == "darwin") and extra == 'remote'
Requires-Dist: grpcio !=1.48.0,<=1.51.3,>=1.42.0 ; (python_version >= "3.10" and sys_platform != "darwin") and extra == 'remote'
Requires-Dist: grpcio !=1.48.0,<=1.49.1,>=1.42.0 ; (python_version >= "3.10" and sys_platform == "darwin") and extra == 'remote'
Provides-Extra: runpod
Requires-Dist: runpod >=1.5.1 ; extra == 'runpod'
Provides-Extra: scp
Requires-Dist: ray[default] !=2.6.0,>=2.2.0 ; extra == 'scp'
Provides-Extra: vsphere
Requires-Dist: pyvmomi ==8.0.1.0.2 ; extra == 'vsphere'
